theanswer/__init__.py
theanswer-0.1.dist-info/DESCRIPTION.rst
theanswer-0.1.dist-info/METADATA
theanswer-0.1.dist-info/RECORD
theanswer-0.1.dist-info/WHEEL
theanswer-0.1.dist-info/metadata.json
theanswer-0.1.dist-info/top_level.txt
