Metadata-Version: 2.0
Name: theanswer
Version: 0.1
Summary: answer to the ultimate question
Home-page: https://github.com/zabop/PyPIattempt
Author: Pal Szabo
Author-email: szabopal96@gmail.com
License: MIT
Platform: UNKNOWN
